CHASM/__init__.py
CHASM/atmabs.dat
CHASM/atmosphere.py
CHASM/axis.py
CHASM/charged_particle.py
CHASM/charged_particle_ABC.py
CHASM/cherenkov_photon.py
CHASM/cherenkov_photon_array.py
CHASM/cherenkov_yield.py
CHASM/chpy.yml
CHASM/counter_array.py
CHASM/generate_Cherenkov.py
CHASM/shower.py
CHASM/simulation.py
CHASM/yield_table.py
CHASM/data/Y_lX_array.npz
CHASM/data/__init__.py
CHASM/data/abstable.npz
CHASM/data/gg_t_delta_theta_2020_normalized.npz
CHASM/data/gg_t_delta_theta_doubled.npz
CHASM/data/gg_t_delta_theta_lX_-2_to_-1.npz
CHASM/data/gg_t_delta_theta_lX_-3_to_-2.npz
CHASM/data/gg_t_delta_theta_lX_-4_to_-3.npz
CHASM/data/gg_t_delta_theta_lX_-5_to_-4.npz
CHASM/data/gg_t_delta_theta_lX_-6_to_-5.npz
CHASM/data/gg_t_delta_theta_mc.npz
CHASM/data/n_t_lX_of_t_lX.npz
CHASM/data/sample_corsika_data.npz
CHASM/data/y_t_delta.npz
CHASM/data/y_t_delta_lX_-2_to_-1.npz
CHASM/data/y_t_delta_lX_-3_to_-2.npz
CHASM/data/y_t_delta_lX_-4_to_-3.npz
CHASM/data/y_t_delta_lX_-5_to_-4.npz
CHASM/data/y_t_delta_lX_-6_to_-5.npz
CHASM_NuSpacesim-0.0.6.dist-info/METADATA
CHASM_NuSpacesim-0.0.6.dist-info/WHEEL
CHASM_NuSpacesim-0.0.6.dist-info/top_level.txt
CHASM_NuSpacesim-0.0.6.dist-info/zip-safe
CHASM_NuSpacesim-0.0.6.dist-info/RECORD
