Metadata-Version: 2.1
Name: CHASM-NuSpacesim
Version: 0.0.6
Summary: CHerenkov Air Shower Model
Author-email: Isaac Buckland <ikepc1@gmail.com>
Project-URL: Homepage, https://github.com/ikepc1/CHASM_NuSpacesim
Classifier: Programming Language :: Python :: 3
Classifier: License :: OSI Approved :: MIT License
Classifier: Operating System :: OS Independent
Requires-Python: >=3.10
Requires-Dist: eventio
Requires-Dist: h5py
Requires-Dist: ipympl
Requires-Dist: jupyter
Requires-Dist: matplotlib
Requires-Dist: numpy (>=1.21)
Requires-Dist: scipy
